{
  "hardware": {
    "TPU v5p (per chip)": {
      "compute_tflops": 459,
      "bw_tb_s": 4.8,
      "ridge": 95.625
    },
    "TPU v5p (4-chip system)": {
      "compute_tflops": 1836,
      "bw_tb_s": 19.2,
      "ridge": 95.625
    },
    "H100 SXM (published)": {
      "compute_tflops": 990,
      "bw_tb_s": 3.35,
      "ridge": 295.5223880597015
    },
    "RTX 2000 Ada": {
      "compute_tflops": 12.0,
      "bw_tb_s": 0.288,
      "ridge": 41.66666666666667
    }
  },
  "components": {
    "ffn": [
      {
        "K": 1,
        "flops": 149422080,
        "bytes_total": 149490688,
        "bytes_weight": 149422080,
        "bytes_activation": 68608,
        "oi": 1.0,
        "tpu_regime": "MEMORY-BOUND",
        "h100_regime": "MEMORY-BOUND"
      },
      {
        "K": 16,
        "flops": 2390753280,
        "bytes_total": 150519808,
        "bytes_weight": 149422080,
        "bytes_activation": 1097728,
        "oi": 15.9,
        "tpu_regime": "MEMORY-BOUND",
        "h100_regime": "MEMORY-BOUND"
      },
      {
        "K": 32,
        "flops": 4781506560,
        "bytes_total": 151617536,
        "bytes_weight": 149422080,
        "bytes_activation": 2195456,
        "oi": 31.5,
        "tpu_regime": "MEMORY-BOUND",
        "h100_regime": "MEMORY-BOUND"
      },
      {
        "K": 64,
        "flops": 9563013120,
        "bytes_total": 153812992,
        "bytes_weight": 149422080,
        "bytes_activation": 4390912,
        "oi": 62.2,
        "tpu_regime": "MEMORY-BOUND",
        "h100_regime": "MEMORY-BOUND"
      },
      {
        "K": 128,
        "flops": 19126026240,
        "bytes_total": 158203904,
        "bytes_weight": 149422080,
        "bytes_activation": 8781824,
        "oi": 120.9,
        "tpu_regime": "COMPUTE-BOUND",
        "h100_regime": "MEMORY-BOUND"
      },
      {
        "K": 256,
        "flops": 38252052480,
        "bytes_total": 166985728,
        "bytes_weight": 149422080,
        "bytes_activation": 17563648,
        "oi": 229.1,
        "tpu_regime": "COMPUTE-BOUND",
        "h100_regime": "MEMORY-BOUND"
      },
      {
        "K": 512,
        "flops": 76504104960,
        "bytes_total": 184549376,
        "bytes_weight": 149422080,
        "bytes_activation": 35127296,
        "oi": 414.5,
        "tpu_regime": "COMPUTE-BOUND",
        "h100_regime": "COMPUTE-BOUND"
      },
      {
        "K": 1024,
        "flops": 153008209920,
        "bytes_total": 219676672,
        "bytes_weight": 149422080,
        "bytes_activation": 70254592,
        "oi": 696.5,
        "tpu_regime": "COMPUTE-BOUND",
        "h100_regime": "COMPUTE-BOUND"
      }
    ],
    "attention_qkt": {
      "64": [
        {
          "K": 1,
          "L": 64,
          "flops": 655360,
          "bytes_kv_cache": 163840,
          "bytes_q": 5120,
          "bytes_total": 174080,
          "oi": 3.8,
          "tpu_regime": "MEMORY-BOUND",
          "h100_regime": "MEMORY-BOUND"
        },
        {
          "K": 16,
          "L": 64,
          "flops": 10485760,
          "bytes_kv_cache": 163840,
          "bytes_q": 81920,
          "bytes_total": 327680,
          "oi": 32.0,
          "tpu_regime": "MEMORY-BOUND",
          "h100_regime": "MEMORY-BOUND"
        },
        {
          "K": 32,
          "L": 64,
          "flops": 20971520,
          "bytes_kv_cache": 163840,
          "bytes_q": 163840,
          "bytes_total": 491520,
          "oi": 42.7,
          "tpu_regime": "MEMORY-BOUND",
          "h100_regime": "MEMORY-BOUND"
        },
        {
          "K": 64,
          "L": 64,
          "flops": 41943040,
          "bytes_kv_cache": 163840,
          "bytes_q": 327680,
          "bytes_total": 819200,
          "oi": 51.2,
          "tpu_regime": "MEMORY-BOUND",
          "h100_regime": "MEMORY-BOUND"
        },
        {
          "K": 128,
          "L": 64,
          "flops": 83886080,
          "bytes_kv_cache": 163840,
          "bytes_q": 655360,
          "bytes_total": 1474560,
          "oi": 56.9,
          "tpu_regime": "MEMORY-BOUND",
          "h100_regime": "MEMORY-BOUND"
        },
        {
          "K": 256,
          "L": 64,
          "flops": 167772160,
          "bytes_kv_cache": 163840,
          "bytes_q": 1310720,
          "bytes_total": 2785280,
          "oi": 60.2,
          "tpu_regime": "MEMORY-BOUND",
          "h100_regime": "MEMORY-BOUND"
        },
        {
          "K": 512,
          "L": 64,
          "flops": 335544320,
          "bytes_kv_cache": 163840,
          "bytes_q": 2621440,
          "bytes_total": 5406720,
          "oi": 62.1,
          "tpu_regime": "MEMORY-BOUND",
          "h100_regime": "MEMORY-BOUND"
        },
        {
          "K": 1024,
          "L": 64,
          "flops": 671088640,
          "bytes_kv_cache": 163840,
          "bytes_q": 5242880,
          "bytes_total": 10649600,
          "oi": 63.0,
          "tpu_regime": "MEMORY-BOUND",
          "h100_regime": "MEMORY-BOUND"
        }
      ],
      "256": [
        {
          "K": 1,
          "L": 256,
          "flops": 2621440,
          "bytes_kv_cache": 655360,
          "bytes_q": 5120,
          "bytes_total": 665600,
          "oi": 3.9,
          "tpu_regime": "MEMORY-BOUND",
          "h100_regime": "MEMORY-BOUND"
        },
        {
          "K": 16,
          "L": 256,
          "flops": 41943040,
          "bytes_kv_cache": 655360,
          "bytes_q": 81920,
          "bytes_total": 819200,
          "oi": 51.2,
          "tpu_regime": "MEMORY-BOUND",
          "h100_regime": "MEMORY-BOUND"
        },
        {
          "K": 32,
          "L": 256,
          "flops": 83886080,
          "bytes_kv_cache": 655360,
          "bytes_q": 163840,
          "bytes_total": 983040,
          "oi": 85.3,
          "tpu_regime": "MEMORY-BOUND",
          "h100_regime": "MEMORY-BOUND"
        },
        {
          "K": 64,
          "L": 256,
          "flops": 167772160,
          "bytes_kv_cache": 655360,
          "bytes_q": 327680,
          "bytes_total": 1310720,
          "oi": 128.0,
          "tpu_regime": "COMPUTE-BOUND",
          "h100_regime": "MEMORY-BOUND"
        },
        {
          "K": 128,
          "L": 256,
          "flops": 335544320,
          "bytes_kv_cache": 655360,
          "bytes_q": 655360,
          "bytes_total": 1966080,
          "oi": 170.7,
          "tpu_regime": "COMPUTE-BOUND",
          "h100_regime": "MEMORY-BOUND"
        },
        {
          "K": 256,
          "L": 256,
          "flops": 671088640,
          "bytes_kv_cache": 655360,
          "bytes_q": 1310720,
          "bytes_total": 3276800,
          "oi": 204.8,
          "tpu_regime": "COMPUTE-BOUND",
          "h100_regime": "MEMORY-BOUND"
        },
        {
          "K": 512,
          "L": 256,
          "flops": 1342177280,
          "bytes_kv_cache": 655360,
          "bytes_q": 2621440,
          "bytes_total": 5898240,
          "oi": 227.6,
          "tpu_regime": "COMPUTE-BOUND",
          "h100_regime": "MEMORY-BOUND"
        },
        {
          "K": 1024,
          "L": 256,
          "flops": 2684354560,
          "bytes_kv_cache": 655360,
          "bytes_q": 5242880,
          "bytes_total": 11141120,
          "oi": 240.9,
          "tpu_regime": "COMPUTE-BOUND",
          "h100_regime": "MEMORY-BOUND"
        }
      ],
      "512": [
        {
          "K": 1,
          "L": 512,
          "flops": 5242880,
          "bytes_kv_cache": 1310720,
          "bytes_q": 5120,
          "bytes_total": 1320960,
          "oi": 4.0,
          "tpu_regime": "MEMORY-BOUND",
          "h100_regime": "MEMORY-BOUND"
        },
        {
          "K": 16,
          "L": 512,
          "flops": 83886080,
          "bytes_kv_cache": 1310720,
          "bytes_q": 81920,
          "bytes_total": 1474560,
          "oi": 56.9,
          "tpu_regime": "MEMORY-BOUND",
          "h100_regime": "MEMORY-BOUND"
        },
        {
          "K": 32,
          "L": 512,
          "flops": 167772160,
          "bytes_kv_cache": 1310720,
          "bytes_q": 163840,
          "bytes_total": 1638400,
          "oi": 102.4,
          "tpu_regime": "COMPUTE-BOUND",
          "h100_regime": "MEMORY-BOUND"
        },
        {
          "K": 64,
          "L": 512,
          "flops": 335544320,
          "bytes_kv_cache": 1310720,
          "bytes_q": 327680,
          "bytes_total": 1966080,
          "oi": 170.7,
          "tpu_regime": "COMPUTE-BOUND",
          "h100_regime": "MEMORY-BOUND"
        },
        {
          "K": 128,
          "L": 512,
          "flops": 671088640,
          "bytes_kv_cache": 1310720,
          "bytes_q": 655360,
          "bytes_total": 2621440,
          "oi": 256.0,
          "tpu_regime": "COMPUTE-BOUND",
          "h100_regime": "MEMORY-BOUND"
        },
        {
          "K": 256,
          "L": 512,
          "flops": 1342177280,
          "bytes_kv_cache": 1310720,
          "bytes_q": 1310720,
          "bytes_total": 3932160,
          "oi": 341.3,
          "tpu_regime": "COMPUTE-BOUND",
          "h100_regime": "COMPUTE-BOUND"
        },
        {
          "K": 512,
          "L": 512,
          "flops": 2684354560,
          "bytes_kv_cache": 1310720,
          "bytes_q": 2621440,
          "bytes_total": 6553600,
          "oi": 409.6,
          "tpu_regime": "COMPUTE-BOUND",
          "h100_regime": "COMPUTE-BOUND"
        },
        {
          "K": 1024,
          "L": 512,
          "flops": 5368709120,
          "bytes_kv_cache": 1310720,
          "bytes_q": 5242880,
          "bytes_total": 11796480,
          "oi": 455.1,
          "tpu_regime": "COMPUTE-BOUND",
          "h100_regime": "COMPUTE-BOUND"
        }
      ],
      "1024": [
        {
          "K": 1,
          "L": 1024,
          "flops": 10485760,
          "bytes_kv_cache": 2621440,
          "bytes_q": 5120,
          "bytes_total": 2631680,
          "oi": 4.0,
          "tpu_regime": "MEMORY-BOUND",
          "h100_regime": "MEMORY-BOUND"
        },
        {
          "K": 16,
          "L": 1024,
          "flops": 167772160,
          "bytes_kv_cache": 2621440,
          "bytes_q": 81920,
          "bytes_total": 2785280,
          "oi": 60.2,
          "tpu_regime": "MEMORY-BOUND",
          "h100_regime": "MEMORY-BOUND"
        },
        {
          "K": 32,
          "L": 1024,
          "flops": 335544320,
          "bytes_kv_cache": 2621440,
          "bytes_q": 163840,
          "bytes_total": 2949120,
          "oi": 113.8,
          "tpu_regime": "COMPUTE-BOUND",
          "h100_regime": "MEMORY-BOUND"
        },
        {
          "K": 64,
          "L": 1024,
          "flops": 671088640,
          "bytes_kv_cache": 2621440,
          "bytes_q": 327680,
          "bytes_total": 3276800,
          "oi": 204.8,
          "tpu_regime": "COMPUTE-BOUND",
          "h100_regime": "MEMORY-BOUND"
        },
        {
          "K": 128,
          "L": 1024,
          "flops": 1342177280,
          "bytes_kv_cache": 2621440,
          "bytes_q": 655360,
          "bytes_total": 3932160,
          "oi": 341.3,
          "tpu_regime": "COMPUTE-BOUND",
          "h100_regime": "COMPUTE-BOUND"
        },
        {
          "K": 256,
          "L": 1024,
          "flops": 2684354560,
          "bytes_kv_cache": 2621440,
          "bytes_q": 1310720,
          "bytes_total": 5242880,
          "oi": 512.0,
          "tpu_regime": "COMPUTE-BOUND",
          "h100_regime": "COMPUTE-BOUND"
        },
        {
          "K": 512,
          "L": 1024,
          "flops": 5368709120,
          "bytes_kv_cache": 2621440,
          "bytes_q": 2621440,
          "bytes_total": 7864320,
          "oi": 682.7,
          "tpu_regime": "COMPUTE-BOUND",
          "h100_regime": "COMPUTE-BOUND"
        },
        {
          "K": 1024,
          "L": 1024,
          "flops": 10737418240,
          "bytes_kv_cache": 2621440,
          "bytes_q": 5242880,
          "bytes_total": 13107200,
          "oi": 819.2,
          "tpu_regime": "COMPUTE-BOUND",
          "h100_regime": "COMPUTE-BOUND"
        }
      ],
      "2048": [
        {
          "K": 1,
          "L": 2048,
          "flops": 20971520,
          "bytes_kv_cache": 5242880,
          "bytes_q": 5120,
          "bytes_total": 5253120,
          "oi": 4.0,
          "tpu_regime": "MEMORY-BOUND",
          "h100_regime": "MEMORY-BOUND"
        },
        {
          "K": 16,
          "L": 2048,
          "flops": 335544320,
          "bytes_kv_cache": 5242880,
          "bytes_q": 81920,
          "bytes_total": 5406720,
          "oi": 62.1,
          "tpu_regime": "MEMORY-BOUND",
          "h100_regime": "MEMORY-BOUND"
        },
        {
          "K": 32,
          "L": 2048,
          "flops": 671088640,
          "bytes_kv_cache": 5242880,
          "bytes_q": 163840,
          "bytes_total": 5570560,
          "oi": 120.5,
          "tpu_regime": "COMPUTE-BOUND",
          "h100_regime": "MEMORY-BOUND"
        },
        {
          "K": 64,
          "L": 2048,
          "flops": 1342177280,
          "bytes_kv_cache": 5242880,
          "bytes_q": 327680,
          "bytes_total": 5898240,
          "oi": 227.6,
          "tpu_regime": "COMPUTE-BOUND",
          "h100_regime": "MEMORY-BOUND"
        },
        {
          "K": 128,
          "L": 2048,
          "flops": 2684354560,
          "bytes_kv_cache": 5242880,
          "bytes_q": 655360,
          "bytes_total": 6553600,
          "oi": 409.6,
          "tpu_regime": "COMPUTE-BOUND",
          "h100_regime": "COMPUTE-BOUND"
        },
        {
          "K": 256,
          "L": 2048,
          "flops": 5368709120,
          "bytes_kv_cache": 5242880,
          "bytes_q": 1310720,
          "bytes_total": 7864320,
          "oi": 682.7,
          "tpu_regime": "COMPUTE-BOUND",
          "h100_regime": "COMPUTE-BOUND"
        },
        {
          "K": 512,
          "L": 2048,
          "flops": 10737418240,
          "bytes_kv_cache": 5242880,
          "bytes_q": 2621440,
          "bytes_total": 10485760,
          "oi": 1024.0,
          "tpu_regime": "COMPUTE-BOUND",
          "h100_regime": "COMPUTE-BOUND"
        },
        {
          "K": 1024,
          "L": 2048,
          "flops": 21474836480,
          "bytes_kv_cache": 5242880,
          "bytes_q": 5242880,
          "bytes_total": 15728640,
          "oi": 1365.3,
          "tpu_regime": "COMPUTE-BOUND",
          "h100_regime": "COMPUTE-BOUND"
        }
      ]
    },
    "full_layer": {
      "256": [
        {
          "K": 1,
          "L": 256,
          "ffn_oi": 1.0,
          "attn_oi": 0.5,
          "combined_oi": 0.9,
          "weight_pct": 99.6,
          "tpu_regime": "MEMORY-BOUND"
        },
        {
          "K": 16,
          "L": 256,
          "ffn_oi": 15.9,
          "attn_oi": 7.5,
          "combined_oi": 14.3,
          "weight_pct": 98.9,
          "tpu_regime": "MEMORY-BOUND"
        },
        {
          "K": 32,
          "L": 256,
          "ffn_oi": 31.5,
          "attn_oi": 14.8,
          "combined_oi": 28.5,
          "weight_pct": 98.1,
          "tpu_regime": "MEMORY-BOUND"
        },
        {
          "K": 64,
          "L": 256,
          "ffn_oi": 62.2,
          "attn_oi": 29.0,
          "combined_oi": 56.1,
          "weight_pct": 96.6,
          "tpu_regime": "MEMORY-BOUND"
        },
        {
          "K": 128,
          "L": 256,
          "ffn_oi": 120.9,
          "attn_oi": 55.9,
          "combined_oi": 108.8,
          "weight_pct": 93.8,
          "tpu_regime": "COMPUTE-BOUND"
        },
        {
          "K": 256,
          "L": 256,
          "ffn_oi": 229.1,
          "attn_oi": 104.1,
          "combined_oi": 205.6,
          "weight_pct": 88.6,
          "tpu_regime": "COMPUTE-BOUND"
        },
        {
          "K": 512,
          "L": 256,
          "ffn_oi": 414.5,
          "attn_oi": 183.4,
          "combined_oi": 370.1,
          "weight_pct": 79.7,
          "tpu_regime": "COMPUTE-BOUND"
        },
        {
          "K": 1024,
          "L": 256,
          "ffn_oi": 696.5,
          "attn_oi": 296.1,
          "combined_oi": 617.0,
          "weight_pct": 66.5,
          "tpu_regime": "COMPUTE-BOUND"
        }
      ],
      "1024": [
        {
          "K": 1,
          "L": 1024,
          "ffn_oi": 1.0,
          "attn_oi": 0.7,
          "combined_oi": 0.9,
          "weight_pct": 98.5,
          "tpu_regime": "MEMORY-BOUND"
        },
        {
          "K": 16,
          "L": 1024,
          "ffn_oi": 15.9,
          "attn_oi": 10.6,
          "combined_oi": 14.9,
          "weight_pct": 97.8,
          "tpu_regime": "MEMORY-BOUND"
        },
        {
          "K": 32,
          "L": 1024,
          "ffn_oi": 31.5,
          "attn_oi": 20.9,
          "combined_oi": 29.5,
          "weight_pct": 97.1,
          "tpu_regime": "MEMORY-BOUND"
        },
        {
          "K": 64,
          "L": 1024,
          "ffn_oi": 62.2,
          "attn_oi": 41.1,
          "combined_oi": 58.1,
          "weight_pct": 95.6,
          "tpu_regime": "MEMORY-BOUND"
        },
        {
          "K": 128,
          "L": 1024,
          "ffn_oi": 120.9,
          "attn_oi": 79.4,
          "combined_oi": 112.9,
          "weight_pct": 92.9,
          "tpu_regime": "COMPUTE-BOUND"
        },
        {
          "K": 256,
          "L": 1024,
          "ffn_oi": 229.1,
          "attn_oi": 148.6,
          "combined_oi": 213.3,
          "weight_pct": 87.8,
          "tpu_regime": "COMPUTE-BOUND"
        },
        {
          "K": 512,
          "L": 1024,
          "ffn_oi": 414.5,
          "attn_oi": 263.3,
          "combined_oi": 384.4,
          "weight_pct": 79.1,
          "tpu_regime": "COMPUTE-BOUND"
        },
        {
          "K": 1024,
          "L": 1024,
          "ffn_oi": 696.5,
          "attn_oi": 428.7,
          "combined_oi": 641.8,
          "weight_pct": 66.0,
          "tpu_regime": "COMPUTE-BOUND"
        }
      ]
    }
  }
}